gsheets2/__init__.py
gsheets2/admin.py
gsheets2/apps.py
gsheets2/auth.py
gsheets2/decorators.py
gsheets2/gsheets2.py
gsheets2/management/__init__.py
gsheets2/management/commands/__init__.py
gsheets2/management/commands/syncgsheets.py
gsheets2/migrations/0001_initial.py
gsheets2/migrations/0002_accesscredentials_created_time.py
gsheets2/migrations/0003_alter_accesscredentials_id.py
gsheets2/migrations/__init__.py
gsheets2/mixins.py
gsheets2/mixins_old.py
gsheets2/models.py
gsheets2/settings.py
gsheets2/signals/__init__.py
gsheets2/tests.py
gsheets2/urls.py
gsheets2/views.py
gsheets2-0.1.4.dist-info/METADATA
gsheets2-0.1.4.dist-info/WHEEL
gsheets2-0.1.4.dist-info/RECORD
